wattleflow/core/__init__.py
wattleflow/core/_version.py
wattleflow/core/behavioral.py
wattleflow/core/concurrent.py
wattleflow/core/creational.py
wattleflow/core/framework.py
wattleflow/core/structural.py
wattleflow/core/transactional.py
wattleflow/logo/wattleflow.png
wattleflow-0.0.0.29.dist-info/licenses/LICENSE
wattleflow-0.0.0.29.dist-info/METADATA
wattleflow-0.0.0.29.dist-info/WHEEL
wattleflow-0.0.0.29.dist-info/top_level.txt
wattleflow-0.0.0.29.dist-info/RECORD
