Metadata-Version: 2.4
Name: wattleflow
Version: 0.0.0.29
Summary: Wattleflow Core for Python
Home-page: https://github.com/wattleflow/core.git
Author: wattleFlow
Author-email: wattleflow <wattleflow@outlook.com>
License:                                  Apache License
Project-URL: homepage, https://github.com/wattleflow/core.git
Project-URL: repository, https://github.com/wattleflow/core.git
Project-URL: documentation, https://github.com/wattleflow/docs.git
Keywords: wattleflow,framework,core,library,design,patterns,python,library,software engineering
Classifier: Development Status :: 5 - Production/Stable
Classifier: Programming Language :: Python :: 3.8
Classifier: Programming Language :: Python :: 3.9
Classifier: Programming Language :: Python :: 3.10
Classifier: Programming Language :: Python :: 3.11
Classifier: Programming Language :: Python :: 3.12
Classifier: Programming Language :: Python :: 3.13
Classifier: Operating System :: OS Independent
Classifier: Intended Audience :: Developers
Classifier: Topic :: Software Development :: Libraries
Requires-Python: >=3.8
License-File: LICENSE
Dynamic: author
Dynamic: home-page
Dynamic: license-file
Dynamic: requires-python
